skeleton_refinement/__init__.py
skeleton_refinement/deformable_registration.py
skeleton_refinement/expectation_maximization_registration.py
skeleton_refinement/io.py
skeleton_refinement/stochastic_registration.py
skeleton_refinement/utilities.py
skeleton_refinement/cli/__init__.py
skeleton_refinement/cli/refine_skeleton.py
skeleton_refinement-0.1.1.dist-info/licenses/LICENSE
skeleton_refinement-0.1.1.dist-info/METADATA
skeleton_refinement-0.1.1.dist-info/WHEEL
skeleton_refinement-0.1.1.dist-info/entry_points.txt
skeleton_refinement-0.1.1.dist-info/top_level.txt
skeleton_refinement-0.1.1.dist-info/RECORD
