Metadata-Version: 2.4
Name: skeleton_refinement
Version: 0.1.1
Summary: Skeletonization of Plant Point Cloud Data Using Stochastic Optimization Framework.
Author-email: Ayan Chaudhury <ayanchaudhury.cs@gmail.com>, Christophe Godin <christophe.godin@inria.fr>
Maintainer-email: Jonathan Legrand <jonathan.legrand@ens-lyon.fr>
License: GPL-3.0-or-later
Project-URL: homepage, https://romi-project.eu/
Project-URL: documentation, https://docs.romi-project.eu/plant_imager/
Project-URL: source, https://github.com/romi/skeleton_refinement
Project-URL: issues, https://github.com/romi/skeleton_refinement/issues
Keywords: Robotics for Microfarms,ROMI,Skeleton,Point-cloud,Stochastic Optimization,Gaussian Mixture Models,Expectation Maximization
Classifier: Programming Language :: Python :: 3
Classifier: Development Status :: 4 - Beta
Classifier: Intended Audience :: Science/Research
Classifier: Topic :: Scientific/Engineering :: Bio-Informatics
Classifier: Topic :: Software Development :: Libraries :: Python Modules
Classifier: Operating System :: OS Independent
Classifier: Natural Language :: English
Requires-Python: >=3.8
License-File: LICENSE
Requires-Dist: matplotlib
Requires-Dist: networkx
Requires-Dist: numpy
Requires-Dist: plyfile
Requires-Dist: scikit-learn
Provides-Extra: doc
Requires-Dist: mkdocs; extra == "doc"
Requires-Dist: mkdocs-material; extra == "doc"
Requires-Dist: mkdocstrings[python]; extra == "doc"
Requires-Dist: pymdown-extensions; extra == "doc"
Requires-Dist: markdown-exec[ansi]; extra == "doc"
Requires-Dist: mkdocs-gen-files; extra == "doc"
Requires-Dist: mkdocs-literate-nav; extra == "doc"
Requires-Dist: mkdocs-section-index; extra == "doc"
Provides-Extra: test
Requires-Dist: nose2[coverage]; extra == "test"
Requires-Dist: coverage[toml]; extra == "test"
Provides-Extra: nb
Requires-Dist: notebook; extra == "nb"
Requires-Dist: ipywidgets; extra == "nb"
Requires-Dist: plotly; extra == "nb"
Dynamic: license-file
